{
  "multipart": [
	{
	  "apply": {"model": "powah:block/cable_hardened"}
	}, {
	  "when": {
		"north": true
	  },
	  "apply": {"model": "powah:block/cable_multipart_hardened"}
	},
	{
	  "when": {
		"east": true
	  },
	  "apply": {"model": "powah:block/cable_multipart_hardened", "y": 90}
	},
	{
	  "when": {
		"south": true
	  },
	  "apply": {"model": "powah:block/cable_multipart_hardened", "x": 180}
	},
	{
	  "when": {
		"west": true
	  },
	  "apply": {"model": "powah:block/cable_multipart_hardened", "y": 270}
	},
	{
	  "when": {
		"up": true
	  },
	  "apply": {"model": "powah:block/cable_multipart_hardened", "x": 270}
	},
	{
	  "when": {
		"down": true
	  },
	  "apply": {"model": "powah:block/cable_multipart_hardened", "x": 90}
	}
  ]
}